{
    "DNDConfig": null,
    "_enabled_": false,
    "_margin_": [
        0,
        0,
        0,
        0
    ],
    "_skin_": "s27285c1a630442880f9be871bc171db",
    "_title_": "TextBox",
    "addWidgetsdone": false,
    "allboxes": [],
    "canUpdateUI": true,
    "children": [
        "hBoxTextBox",
        "label192735980024525",
        "textfield2192735980025983",
        "label192735980024515",
        "textfield211798972521729",
        "label192735980024550",
        "textfield2192735980024559",
        "label192735980024575",
        "textfield2192735980024586",
        "label192735980024608",
        "textfield2192735980024620",
        "label192735980024647",
        "textfield2192735980024664",
        "label118082077327312",
        "textfield2118082077327321"
    ],
    "containerheightreference": 1,
    "containerweight": 100,
    "displayorientation": 3,
    "enabledforidletimeout": false,
    "footeroverlap": false,
    "headeroverlap": false,
    "id": "frmTbx",
    "info": null,
    "initdone": false,
    "intransitionconfig": {
        "formTransition": "None"
    },
    "ismodal": false,
    "isvisible": true,
    "kuid": "frmTbxSPABlackberry",
    "margininpixel": false,
    "menuposition": 2,
    "name": "kony.ui.Form2",
    "needappmenu": true,
    "outtransitionconfig": {
        "formTransition": "None"
    },
    "percent": true,
    "restorewidgetprototypes": true,
    "retainscrollposition": false,
    "spa": {
        "@class": "com.kony.gen.viz.model.container.property.form.SPAFormProperty",
        "inTransitionConfig": {
            "formTransition": "leftCenter"
        },
        "isModal": false,
        "needAppMenu": false,
        "outTransitionConfig": {
            "formTransition": "none"
        },
        "psp": {
            "dockableAppMenu": true,
            "dockableFooter": true,
            "dockableHeader": true
        }
    },
    "spabb": {
        "@class": "com.kony.gen.viz.model.container.property.form.SPABBFormProperty",
        "needAppMenu": true,
        "render": true
    },
    "templateType": "forms",
    "titleBarSkin": "s451cd155d3649ac9e2793e49e50285d",
    "titlebar": true,
    "transparencybehindthepopup": 100,
    "type": 3,
    "wType": "Form",
    "widgetalignment": 1
}