{
    "DNDConfig": null,
    "_enabled_": false,
    "_margin_": [
        2,
        2,
        2,
        2
    ],
    "_padding_": [
        2,
        1,
        1,
        1
    ],
    "_skin_": "s6a7d85de2ac420a868850c3613b851e",
    "_text_": "Label with Helvetica font",
    "_wrapping_": 2,
    "canUpdateUI": true,
    "containerweight": 50,
    "contentalignment": 1,
    "desktopweb": {
        "@class": "com.kony.gen.viz.model.component.property.label.DesktopWebLabelProperty",
        "psp": {
            "textCopyable": false
        },
        "render": true
    },
    "hexpand": true,
    "id": "label118082077326332",
    "info": null,
    "isvisible": true,
    "kiosk": {
        "@class": "com.kony.gen.viz.model.component.property.label.KioskLabelProperty",
        "render": true
    },
    "kuid": "p2kwiet12889314955430",
    "margininpixel": false,
    "name": "kony.ui.Label",
    "paddinginpixel": false,
    "parent": "hbox68508043441808",
    "pf": "frmLabels",
    "spa": {
        "@class": "com.kony.gen.viz.model.component.property.label.SPALabelProperty",
        "psp": {
            "textCopyable": false
        }
    },
    "tooltip": "",
    "vexpand": false,
    "wType": "Label",
    "widgetalignment": 5
}