{
    "DNDConfig": null,
    "_enabled_": false,
    "_skin_": "s0d5208f9a9845d0a0fd3f8dcf776c16",
    "_text_": "Label",
    "_wrapping_": 2,
    "canUpdateUI": true,
    "containerweight": 100,
    "contentalignment": 4,
    "desktopweb": {
        "@class": "com.kony.gen.viz.model.component.property.label.DesktopWebLabelProperty",
        "_margin_": [
            0,
            0,
            0,
            0
        ],
        "_padding_": [
            0,
            0,
            2,
            0
        ],
        "margin": [
            0,
            0,
            0,
            0
        ],
        "marginInPixel": false,
        "padding": [
            0,
            0,
            2,
            0
        ],
        "paddingInPixel": false,
        "psp": {
            "textCopyable": false
        },
        "render": true
    },
    "hexpand": true,
    "id": "lblSecHdr2",
    "info": null,
    "isvisible": true,
    "kiosk": {
        "@class": "com.kony.gen.viz.model.component.property.label.KioskLabelProperty",
        "render": true
    },
    "kuid": "p2kwiet12889314956286",
    "name": "kony.ui.Label",
    "parent": "vbox120944992024383",
    "pf": "tempSegHdr2",
    "spa": {
        "@class": "com.kony.gen.viz.model.component.property.label.SPALabelProperty",
        "psp": {
            "textCopyable": false
        }
    },
    "tooltip": "",
    "vexpand": false,
    "wType": "Label",
    "widgetalignment": 4
}