{
    "DNDConfig": null,
    "_enabled_": false,
    "_margin_": [
        2,
        2,
        2,
        2
    ],
    "_orientation_": 1,
    "_padding_": [
        0,
        0,
        0,
        0
    ],
    "_percent_": true,
    "_render_": true,
    "_resize_": true,
    "activefocusskin": "s011ba0c399545058803761048621d91",
    "activeskin": "sdacddcc0c744edbabcae93b32bea3b4",
    "activetab": 2,
    "activetabs": [],
    "allboxes": [],
    "canUpdateUI": true,
    "children": [
        "tab193203698711086",
        "tab193203698711107",
        "tab193203698711163"
    ],
    "containerheightreference": 1,
    "containerweight": 100,
    "context": {
        "channel": "mobile",
        "formID": "AdvancedWidgetsTab",
        "tabpaneID": "",
        "templateType": "forms",
        "topLevelBox": true
    },
    "desktopweb": {
        "@class": "com.kony.gen.viz.model.container.property.tabpane.DesktopWebTabPaneProperty",
        "_margin_": [
            2,
            2,
            2,
            2
        ],
        "margin": [
            2,
            2,
            2,
            2
        ],
        "marginInPixel": false,
        "render": true,
        "viewType": "tabview"
    },
    "focusskin": "tabFocus",
    "id": "tabpane193203698711085",
    "imageposition": "right",
    "inactiveskin": "s818f70229cd4e88a276f2b381256077",
    "info": null,
    "isvisible": true,
    "kiosk": {
        "@class": "com.kony.gen.viz.model.container.property.tabpane.KioskTabPaneProperty",
        "render": true,
        "viewType": "tabview"
    },
    "kuid": "p2kwiet12889314955754",
    "margininpixel": false,
    "name": "kony.ui.TabPane",
    "paddinginpixel": false,
    "parent": "vbox193203698711084",
    "pf": "frmTabPane",
    "screenlevelwidget": false,
    "spa": {
        "@class": "com.kony.gen.viz.model.container.property.tabpane.SPATabPaneProperty"
    },
    "tabnamealignment": "left",
    "templateType": "forms",
    "toggletabs": false,
    "viewconfig": {
        "collapsibleViewConfig": {
            "imagePosition": "right",
            "tabNameAlignment": "left",
            "toggleTabs": false
        },
        "pageViewConfig": {
            "needPageIndicator": true
        },
        "panoramaViewConfig": {
            "panoramaImage": "",
            "panoramaTitle": "",
            "panoramaTitleImage": ""
        },
        "tabViewConfig": {
            "headerContainerWeight": "",
            "headerPosition": "top",
            "image1": "",
            "image2": ""
        }
    },
    "wType": "TabPane",
    "widgetalignment": 1
}