{
    "DNDConfig": null,
    "_enabled_": false,
    "_margin_": [
        2,
        2,
        2,
        2
    ],
    "_padding_": [
        1,
        1,
        1,
        1
    ],
    "_skin_": "s3ab48977dd441f6a76ab5d2fe0e0526",
    "_text_": "Label",
    "_wrapping_": 2,
    "canUpdateUI": true,
    "containerweight": 100,
    "contentalignment": 4,
    "desktopweb": {
        "@class": "com.kony.gen.viz.model.component.property.label.DesktopWebLabelProperty",
        "psp": {
            "textCopyable": false
        },
        "render": true
    },
    "hexpand": true,
    "id": "label118085056485802",
    "info": null,
    "isvisible": true,
    "kiosk": {
        "@class": "com.kony.gen.viz.model.component.property.label.KioskLabelProperty",
        "render": true
    },
    "kuid": "p2kwiet12889314955637",
    "margininpixel": false,
    "name": "kony.ui.Label",
    "paddinginpixel": false,
    "parent": "vbox1288931495399",
    "pf": "vbox1288931495399",
    "spa": {
        "@class": "com.kony.gen.viz.model.component.property.label.SPALabelProperty",
        "psp": {
            "textCopyable": false
        }
    },
    "tooltip": "",
    "vexpand": false,
    "wType": "Label",
    "widgetalignment": 5
}